MANIFEST.in
NEWS.txt
README.txt
setup.py
src/motivator/__init__.py
src/motivator.egg-info/PKG-INFO
src/motivator.egg-info/SOURCES.txt
src/motivator.egg-info/dependency_links.txt
src/motivator.egg-info/entry_points.txt
src/motivator.egg-info/not-zip-safe
src/motivator.egg-info/requires.txt
src/motivator.egg-info/top_level.txt