Metadata-Version: 1.0
Name: motivator
Version: 1.0a3
Summary: Motivate oneself with a phrase that can be repeated
Home-page: http://bitbucket.org/srid/motivator
Author: srid
Author-email: srid@nearfar.org
License: MIT
Platform: UNKNOWN
